<?xml version="1.0" encoding="utf-8" ?>
<dwsync>
<file name="fotos nuevas 086.jpg" local="129220667767031250" remote="129220666690000000" testing="0" />
<file name="fotos nuevas 087.jpg" local="129220667772031250" remote="129220666690000000" testing="0" />
<file name="fotos nuevas 088.jpg" local="129220667776406250" remote="129220666690000000" testing="0" />
<file name="fotos nuevas 089.jpg" local="129220667780625000" remote="129220666690000000" testing="0" />
<file name="fotos nuevas 090.jpg" local="129220667784843750" remote="129220666690000000" testing="0" />
<file name="fotos nuevas 091.jpg" local="129220667789375000" remote="129220666690000000" testing="0" />
<file name="fotos nuevas 092.jpg" local="129220667793906250" remote="129220666690000000" testing="0" />
<file name="fotos nuevas 093.jpg" local="129220667798437500" remote="129220666690000000" testing="0" />
<file name="fotos nuevas 094.jpg" local="129220667802812500" remote="129220666690000000" testing="0" />
<file name="fotos nuevas 095.jpg" local="129220667807187500" remote="129220666690000000" testing="0" />
<file name="fotos nuevas 096.jpg" local="129220667811406250" remote="129220666690000000" testing="0" />
<file name="fotos nuevas 097.jpg" local="129220667815781250" remote="129220666690000000" testing="0" />
<file name="fotos nuevas 098.jpg" local="129220667820000000" remote="129220666690000000" testing="0" />
<file name="fotos nuevas 099.jpg" local="129220667824218750" remote="129220666690000000" testing="0" />
<file name="fotos nuevas 100.jpg" local="129220667828593750" remote="129220666690000000" testing="0" />
<file name="fotos nuevas 101.jpg" local="129220667833281250" remote="129220666690000000" testing="0" />
<file name="fotos nuevas 102.jpg" local="129220667838281250" remote="129220666690000000" testing="0" />
<file name="fotos nuevas 103.jpg" local="129220667842656250" remote="129220666690000000" testing="0" />
<file name="fotos nuevas 104.jpg" local="129220667847187500" remote="129220666690000000" testing="0" />
<file name="fotos nuevas 105.jpg" local="129220668111406250" remote="129220666690000000" testing="0" />
<file name="fotos nuevas 106.jpg" local="129220668303750000" remote="129220666690000000" testing="0" />
<file name="fotos nuevas 107.jpg" local="129220667860156250" remote="129220666690000000" testing="0" />
<file name="fotos nuevas 108.jpg" local="129220667864531250" remote="129220666690000000" testing="0" />
<file name="fotos nuevas 109.jpg" local="129220667868750000" remote="129220666690000000" testing="0" />
<file name="fotos nuevas 110.jpg" local="129220667873125000" remote="129220666690000000" testing="0" />
<file name="fotos nuevas 111.jpg" local="129220667877500000" remote="129220666690000000" testing="0" />
<file name="fotos nuevas 112.jpg" local="129220667881718750" remote="129220666690000000" testing="0" />
<file name="fotos nuevas 113.jpg" local="129220668544843750" remote="129220666690000000" testing="0" />
<file name="fotos nuevas 114.jpg" local="129220667890468750" remote="129220666690000000" testing="0" />
<file name="fotos nuevas 115.jpg" local="129220667894843750" remote="129220666690000000" testing="0" />
<file name="fotos nuevas 116.jpg" local="129220668366718750" remote="129220666690000000" testing="0" />
<file name="fotos nuevas 117.jpg" local="129220668662187500" remote="129220666690000000" testing="0" />
<file name="fotos nuevas 118.jpg" local="129220668376406250" remote="129220666690000000" testing="0" />
<file name="fotos nuevas 119.jpg" local="129220668797031250" remote="129220666690000000" testing="0" />
<file name="fotos nuevas 120.jpg" local="129220668895312500" remote="129220666690000000" testing="0" />
<file name="fotos nuevas 121.jpg" local="129220668974687500" remote="129220666690000000" testing="0" />
<file name="fotos nuevas 122.jpg" local="129220669080468750" remote="129220666690000000" testing="0" />
<file name="fotos nuevas 123.jpg" local="129220668396093750" remote="129220666690000000" testing="0" />
<file name="fotos nuevas 124.jpg" local="129220669183906250" remote="129220666690000000" testing="0" />
<file name="fotos nuevas 125.jpg" local="129220668405000000" remote="129220666690000000" testing="0" />
<file name="fotos nuevas 126.jpg" local="129220669306250000" remote="129220666690000000" testing="0" />
<file name="fotos nuevas 127.jpg" local="129220668414062500" remote="129220666690000000" testing="0" />
<file name="fotos nuevas 128.jpg" local="129220668418281250" remote="129220666690000000" testing="0" />
<file name="fotos nuevas 129.jpg" local="129220668422656250" remote="129220666690000000" testing="0" />
<file name="fotos nuevas 130.jpg" local="129220668427031250" remote="129220666690000000" testing="0" />
<file name="fotos nuevas 131.jpg" local="129220668431562500" remote="129220666690000000" testing="0" />
<file name="fotos nuevas 132.jpg" local="129220669428281250" remote="129220666690000000" testing="0" />
<file name="fotos nuevas 133.jpg" local="129220669432968750" remote="129220666690000000" testing="0" />
<file name="fotos nuevas 134.jpg" local="129220669509375000" remote="129220666690000000" testing="0" />
<file name="fotos nuevas 135.jpg" local="129220669513906250" remote="129220666690000000" testing="0" />
<file name="fotos nuevas 136.jpg" local="129220669437656250" remote="129220666690000000" testing="0" />
<file name="fotos nuevas 137.jpg" local="129220669441875000" remote="129220666690000000" testing="0" />
<file name="fotos nuevas 138.jpg" local="129220669446250000" remote="129220666690000000" testing="0" />
<file name="fotos nuevas 139.jpg" local="129220669450625000" remote="129220666690000000" testing="0" />
<file name="fotos nuevas 140.jpg" local="129220669455468750" remote="129220666690000000" testing="0" />
<file name="fotos nuevas 141.jpg" local="129220669459687500" remote="129220666690000000" testing="0" />
<file name="fotos nuevas 142.jpg" local="129220669464062500" remote="129220666690000000" testing="0" />
<file name="fotos nuevas 143.jpg" local="129220669468281250" remote="129220666690000000" testing="0" />
<file name="fotos nuevas 144.jpg" local="129220669472812500" remote="129220666690000000" testing="0" />
<file name="fotos nuevas 145.jpg" local="129220669477031250" remote="129220666690000000" testing="0" />
<file name="fotos nuevas 146.jpg" local="129220669481406250" remote="129220666690000000" testing="0" />
<file name="fotos nuevas 147.jpg" local="129220669485625000" remote="129220666690000000" testing="0" />
<file name="fotos nuevas 148.jpg" local="129220669490312500" remote="129220666690000000" testing="0" />
<file name="fotos nuevas 149.jpg" local="129220669494531250" remote="129220666690000000" testing="0" />
<file name="fotos nuevas 150.jpg" local="129220669498906250" remote="129220666690000000" testing="0" />
</dwsync>