<?xml version="1.0" encoding="utf-8" ?>
<dwsync>
<file name="loginmaestros.html" server="C:/AppServ/www/sitiomapi/" local="129302843818109680" remote="129302843810000000" />
<file name="captura.php" server="C:/AppServ/www/sitiomapi/" local="129302839018493696" remote="129302839010000000" />
<file name="captura2.php" server="C:/AppServ/www/sitiomapi/" local="129116835038776725" remote="129116835030000000" />
<file name="captura3.php" server="C:/AppServ/www/sitiomapi/" local="129103236468673491" remote="129103236460000000" />
<file name="intranet.php" server="C:/AppServ/www/sitiomapi/" local="129072837065939659" remote="129072837060000000" />
<file name="insertar.php" server="C:/AppServ/www/sitiomapi/" local="129097139421845041" remote="129097139420000000" />
<file name="loginmaestros.php" server="C:/AppServ/www/sitiomapi/" local="129097139423249044" remote="129097139420000000" />
<file name="capturatareas.php" server="C:/AppServ/www/sitiomapi/" local="129302843154722118" remote="129302843150000000" />
<file name="listatareas.php" server="C:/AppServ/www/sitiomapi/" local="129103802499841787" remote="129103802490000000" />
<file name="guardartarea.php" server="C:/AppServ/www/sitiomapi/" local="129073886553767431" remote="129073886550000000" />
<file name="menu.php" server="C:/AppServ/www/sitiomapi/" local="129103328633749143" remote="129103328630000000" />
<file name="capturaravisos.php" server="C:/AppServ/www/sitiomapi/" local="129103265204774822" remote="129103265200000000" />
<file name="guardaraviso.php" server="C:/AppServ/www/sitiomapi/" local="129073950592810255" remote="129073950590000000" />
<file name="cargar_cumpleanos.php" server="C:/AppServ/www/sitiomapi/" local="129103335811512018" remote="129103335810000000" />
<file name="guardarcumpleanos.php" server="C:/AppServ/www/sitiomapi/" local="129078982646518698" remote="129078982640000000" />
<file name="menu_admin.php" server="C:/AppServ/www/sitiomapi/" local="129249461924690790" remote="129249461920000000" />
<file name="consulta.php" server="C:/AppServ/www/sitiomapi/" local="129103333121668168" remote="129103333120000000" />
<file name="datos_consulta.php" server="C:/AppServ/www/sitiomapi/" local="129302843487800971" remote="129302843480000000" />
<file name="consulta_tareas.php" server="C:/AppServ/www/sitiomapi/" local="129103333214453475" remote="129103333210000000" />
<file name="datos_consulta_tareas.php" server="C:/AppServ/www/sitiomapi/" local="129302843656200488" remote="129302843650000000" />
<file name="borraravisos.php" server="C:/AppServ/www/sitiomapi/" local="129249462709735692" remote="129249462700000000" />
<file name="borraravisos.php" server="C:/AppServ/www/sitiomapi" local="129249455149993299" remote="129249455140000000" />
<file name="borrar_aviso.php" server="C:/AppServ/www/sitiomapi/" local="129249462831652665" remote="129249462830000000" />
</dwsync>